setup.py
filepicker/__init__.py
filepicker/filepicker_client.py
filepicker/filepicker_file.py
filepicker/filepicker_policy.py
filepicker/version.py
filepicker.egg-info/PKG-INFO
filepicker.egg-info/SOURCES.txt
filepicker.egg-info/dependency_links.txt
filepicker.egg-info/requires.txt
filepicker.egg-info/top_level.txt